pybyte/__init__.py
pybyte/byte.py
pybyte/default_thumbnail.jpg
pybyte/endpoints.py
pybyte/feed.py
pybyte/post.py
pybyte/session.py
pybyte/user.py
pybyte-0.1.8.dist-info/METADATA
pybyte-0.1.8.dist-info/WHEEL
pybyte-0.1.8.dist-info/top_level.txt
pybyte-0.1.8.dist-info/RECORD
