Metadata-Version: 2.1
Name: pybyte
Version: 0.1.8
Summary: Byte API Wrapper for Python
Home-page: https://github.com/ms7m/py-byte
Author: Mustafa Mohamed
Author-email: mustafa@ms7m.me
License: MIT
Platform: UNKNOWN
Classifier: License :: OSI Approved :: MIT License
Classifier: Programming Language :: Python
Classifier: Programming Language :: Python :: 3
Classifier: Programming Language :: Python :: 3.6
Classifier: Programming Language :: Python :: Implementation :: CPython
Classifier: Programming Language :: Python :: Implementation :: PyPy
Requires-Python: >=3.6.0
Requires-Dist: requests
Requires-Dist: arrow
Requires-Dist: loguru
Requires-Dist: ffmpy
